{
  "$id": "3389099981",
  "$schema": "http://json-schema.org/draft-07/schema#",
  "description": "The allow_off_hand component determines whether the item can be placed in the off hand slot of the inventory.",
  "oneOf": [
    {
      "type": "boolean"
    },
    {
      "properties": {
        "value": {
          "default": false,
          "description": "Determines whether the item can be placed in the off hand slot.",
          "type": "boolean"
        }
      },
      "type": "object"
    }
  ],
  "title": "minecraft:allow_off_hand",
  "x-format-version": "1.20.50"
}