{
  "$id": "2960610777",
  "$schema": "http://json-schema.org/draft-07/schema#",
  "description": "Conditions that need to be satisfied for a specific effect of a kinetic weapon to be applied.",
  "properties": {
    "max_duration": {
      "default": -1,
      "description": "Time, in ticks, during which the effect can be applied after \"delay\" elapses. If negative, the effect is applied indefinitely.",
      "maximum": 32767,
      "minimum": -32768,
      "type": "integer"
    },
    "min_relative_speed": {
      "default": 0,
      "description": "Minimum relative speed of the user with respect to the target (projected onto the view vector via a dot product) required for the effect to be applied.",
      "maximum": 3.4028234663852886e+38,
      "minimum": 0,
      "type": "number"
    },
    "min_speed": {
      "default": 0,
      "description": "Minimum user's speed (projected onto the view vector via a dot product) required for the effect to be applied.",
      "maximum": 3.4028234663852886e+38,
      "minimum": 0,
      "type": "number"
    }
  },
  "title": "minecraft:kinetic_weapon kinetic_effect_conditions",
  "type": "object",
  "x-format-version": "1.21.90"
}