{
  "$id": "2236411444",
  "$schema": "http://json-schema.org/draft-07/schema#",
  "definitions": {
    "1644558368": {
      "properties": {
        "input": {
          "$ref": "#/definitions/3178719147"
        },
        "nodes": {
          "$ref": "#/definitions/2325482181"
        },
        "type": {
          "pattern": "^bezier_chain$",
          "type": "string"
        }
      },
      "required": [
        "input",
        "nodes",
        "type"
      ],
      "title": "particle_curve_bezier_chain",
      "type": "object"
    },
    "2267778531": {
      "oneOf": [
        {
          "type": "string"
        },
        {
          "properties": {
            "expression": {
              "type": "string"
            },
            "version": {
              "maximum": 32767,
              "minimum": -32768,
              "type": "integer"
            }
          },
          "required": [
            "expression",
            "version"
          ],
          "type": "object"
        }
      ],
      "title": "Molang string"
    },
    "2325482181": {
      "additionalProperties": {
        "$ref": "#/definitions/2334075625"
      },
      "title": "particle_curve_bezier_chain node_map",
      "type": "object"
    },
    "2334075625": {
      "$ref": "#/definitions/963106671",
      "title": "particle_curve_bezier_chain node"
    },
    "2589586811": {
      "properties": {
        "horizontal_range": {
          "$ref": "#/definitions/3178719147",
          "default": 1
        },
        "input": {
          "$ref": "#/definitions/3178719147"
        },
        "nodes": {
          "items": {
            "$ref": "#/definitions/3178719147"
          },
          "type": "array"
        },
        "type": {
          "$ref": "#/definitions/2715320761"
        }
      },
      "required": [
        "input",
        "nodes",
        "type"
      ],
      "title": "particle_curve_linear",
      "type": "object"
    },
    "2715320761": {
      "title": "hashed_string",
      "type": "string"
    },
    "3178719147": {
      "oneOf": [
        {
          "$ref": "#/definitions/2267778531"
        },
        {
          "maximum": 3.4028234663852886e+38,
          "minimum": 1.1754943508222875e-38,
          "type": "number"
        }
      ],
      "title": "Molang expression"
    },
    "963106671": {
      "properties": {
        "left_slope": {
          "maximum": 3.4028234663852886e+38,
          "minimum": 1.1754943508222875e-38,
          "type": "number"
        },
        "left_value": {
          "maximum": 3.4028234663852886e+38,
          "minimum": 1.1754943508222875e-38,
          "type": "number"
        },
        "right_slope": {
          "maximum": 3.4028234663852886e+38,
          "minimum": 1.1754943508222875e-38,
          "type": "number"
        },
        "right_value": {
          "maximum": 3.4028234663852886e+38,
          "minimum": 1.1754943508222875e-38,
          "type": "number"
        },
        "slope": {
          "maximum": 3.4028234663852886e+38,
          "minimum": 1.1754943508222875e-38,
          "type": "number"
        },
        "value": {
          "maximum": 3.4028234663852886e+38,
          "minimum": 1.1754943508222875e-38,
          "type": "number"
        }
      },
      "title": "particle_curve_bezier_chain node_proxy",
      "type": "object"
    }
  },
  "oneOf": [
    {
      "$ref": "#/definitions/2589586811"
    },
    {
      "$ref": "#/definitions/1644558368"
    }
  ],
  "title": "particle_curve",
  "x-format-version": "1.21.0"
}